geoip/__init__.py
geoip/geoip.py
geoip/ip2nation.zip
geoip/ipinfo.py
geoip/utillx.py
geoip2nation3-0.2.0.data/scripts/geoip.py
geoip2nation3-0.2.0.dist-info/METADATA
geoip2nation3-0.2.0.dist-info/RECORD
geoip2nation3-0.2.0.dist-info/WHEEL
geoip2nation3-0.2.0.dist-info/top_level.txt
