Metadata-Version: 2.1
Name: geoip2nation3
Version: 0.2.0
Summary: Convert ip addresses to a country using ip2nation db in memory.
Home-page: https://github.com/pydanny/geoip2nation
Author: Daniel Roy Greenfeld
Author-email: pydanny@gmail.com
License: MIT
Platform: UNKNOWN
Classifier: Development Status :: 4 - Beta
Classifier: Intended Audience :: Developers
Classifier: License :: OSI Approved :: BSD License
Classifier: Natural Language :: English
Classifier: Programming Language :: Python :: 3
Classifier: Programming Language :: Python :: 3.6
